{
  "node_id": "AQ-11",
  "status_code": 201,
  "error": "{\n  \"m2m:cin\" : {\n    \"ty\" : 4,\n    \"ri\" : \"D4465121\",\n    \"pi\" : \"R15637\",\n    \"ct\" : \"20241017T122208\",\n    \"lt\" : \"20241017T122208\",\n    \"rn\" : \"cin4481785\",\n    \"et\" : \"20241027T122208\",\n    \"st\" : 56,\n    \"cr\" : \"SOTIiithWQ1\",\n    \"cs\" : 712,\n    \"con\" : [ {\n      \"timestamp\" : \"2024-10-17T12:22:04.686702\",\n      \"value\" : 25.88\n    }, {\n      \"timestamp\" : \"2024-10-17T12:22:04.686702\",\n      \"value\" : 28.39\n    } ]\n  }\n}"
},
{
  "node_id": "AQ-11",
  "status_code": 201,
  "error": "{\n  \"m2m:cin\" : {\n    \"ty\" : 4,\n    \"ri\" : \"D4465123\",\n    \"pi\" : \"R15637\",\n    \"ct\" : \"20241017T122218\",\n    \"lt\" : \"20241017T122218\",\n    \"rn\" : \"cin4481787\",\n    \"et\" : \"20241027T122218\",\n    \"st\" : 57,\n    \"cr\" : \"SOTIiithWQ1\",\n    \"cs\" : 712,\n    \"con\" : [ {\n      \"timestamp\" : \"2024-10-17T12:22:04.686702\",\n      \"value\" : 25.88\n    }, {\n      \"timestamp\" : \"2024-10-17T12:22:04.686702\",\n      \"value\" : 28.39\n    } ]\n  }\n}"
},
