{
  "node_id": "Ello1234",
  "status_code": 500,
  "error": ""
},
{
  "node_id": "EQWE121313",
  "status_code": 201,
  "error": "{\n  \"m2m:cin\" : {\n    \"ty\" : 4,\n    \"ri\" : \"D4591700\",\n    \"pi\" : \"R15619\",\n    \"ct\" : \"20241109T115852\",\n    \"lt\" : \"20241109T115852\",\n    \"rn\" : \"cin4608400\",\n    \"et\" : \"20241119T115852\",\n    \"st\" : 4,\n    \"cr\" : \"SOTIiithWQ1\",\n    \"cs\" : 58,\n    \"con\" : [ {\n      \"timestamp\" : \"2024-11-09T11:58:48.962225\",\n      \"value\" : 11.03\n    } ]\n  }\n}"
},
