{
  "node_id": "AQ-11",
  "status_code": 201,
  "error": "{\n  \"m2m:cin\" : {\n    \"ty\" : 4,\n    \"ri\" : \"D4618737\",\n    \"pi\" : \"R15637\",\n    \"ct\" : \"20241118T143740\",\n    \"lt\" : \"20241118T143740\",\n    \"rn\" : \"cin4635437\",\n    \"et\" : \"20241128T143740\",\n    \"st\" : 79,\n    \"cr\" : \"SOTIiithWQ1\",\n    \"cs\" : 58,\n    \"con\" : [ {\n      \"timestamp\" : \"2024-11-18T14:37:38.485618\",\n      \"value\" : 20.92\n    } ]\n  }\n}",
  "username": "admin"
},
{
  "node_id": "AQ-11",
  "status_code": 201,
  "error": "{\n  \"m2m:cin\" : {\n    \"ty\" : 4,\n    \"ri\" : \"D4618739\",\n    \"pi\" : \"R15637\",\n    \"ct\" : \"20241118T143750\",\n    \"lt\" : \"20241118T143750\",\n    \"rn\" : \"cin4635439\",\n    \"et\" : \"20241128T143750\",\n    \"st\" : 80,\n    \"cr\" : \"SOTIiithWQ1\",\n    \"cs\" : 58,\n    \"con\" : [ {\n      \"timestamp\" : \"2024-11-18T14:37:38.485618\",\n      \"value\" : 20.92\n    } ]\n  }\n}",
  "username": "admin"
},
